chirp_spectrogram_generator/__init__.py
chirp_spectrogram_generator/generator.py
chirp_spectrogram_generator-0.1.6.dist-info/METADATA
chirp_spectrogram_generator-0.1.6.dist-info/WHEEL
chirp_spectrogram_generator-0.1.6.dist-info/top_level.txt
chirp_spectrogram_generator-0.1.6.dist-info/RECORD
